django_filip/core/__init__.py
django_filip/core/admin.py
django_filip/core/apps.py
django_filip/core/models.py
django_filip/core/tests.py
django_filip/core/views.py
django_filip/core/migrations/__init__.py
django_filip/hent/__init__.py
django_filip/hent/admin.py
django_filip/hent/apps.py
django_filip/hent/models.py
django_filip/hent/tests.py
django_filip/hent/views.py
django_filip/hent/migrations/__init__.py
django_filip/open/__init__.py
django_filip/open/admin.py
django_filip/open/apps.py
django_filip/open/models.py
django_filip/open/tests.py
django_filip/open/views.py
django_filip/open/migrations/__init__.py
django_filip/pool/__init__.py
django_filip/pool/admin.py
django_filip/pool/apps.py
django_filip/pool/models.py
django_filip/pool/tests.py
django_filip/pool/views.py
django_filip/pool/migrations/__init__.py
django_filip/send/__init__.py
django_filip/send/admin.py
django_filip/send/apps.py
django_filip/send/models.py
django_filip/send/tests.py
django_filip/send/views.py
django_filip/send/migrations/__init__.py
django_filip/utils/sftp.py
django_filip-0.1.3.dist-info/METADATA
django_filip-0.1.3.dist-info/WHEEL
django_filip-0.1.3.dist-info/licenses/LICENSE
django_filip-0.1.3.dist-info/RECORD
