Metadata-Version: 2.4
Name: django-filip
Version: 0.1.3
Summary: Utveksling av data mellom regnskapsprogram og nisjesystem
Project-URL: Homepage, https://github.com/stavangerkommune/django-filip
Project-URL: Repository, https://github.com/stavangerkommune/django-filip.git
Author-email: "Erlend D. Handeland" <erlend.dietrich.handeland@stavanger.kommune.no>
License: BSD-3-Clause
License-File: LICENSE
Classifier: Framework :: Django
Classifier: Framework :: Django :: 4.2
Classifier: Framework :: Django :: 5.2
Classifier: License :: OSI Approved :: BSD License
Classifier: Programming Language :: Python :: 3
Requires-Python: >=3.10
Requires-Dist: cryptography>=44.0.2
Requires-Dist: django-matthaios>=0.1.0
Requires-Dist: django>=4.2
Requires-Dist: paramiko>=3.5.1
Requires-Dist: requests>=2.32.3
